Metadata-Version: 1.0
Name: rrp-distributions
Version: 0.2
Summary: Gaussian and Binomial rrp_distributions
Home-page: UNKNOWN
Author: Raden Roy Pradana
Author-email: UNKNOWN
License: UNKNOWN
Platform: UNKNOWN
